opbanner/__init__.py
opbanner/anonbanner.py
opbanner/main.py
opbanner-0.1.7.dist-info/METADATA
opbanner-0.1.7.dist-info/WHEEL
opbanner-0.1.7.dist-info/entry_points.txt
opbanner-0.1.7.dist-info/top_level.txt
opbanner-0.1.7.dist-info/RECORD
