Metadata-Version: 2.4
Name: opbanner
Version: 0.1.7
Summary: A customizable banner display tool for your terminal.
Author-email: ghoste12125 <anonymosmauros@gmail.com>
Project-URL: Homepage, https://github.com/ghoste9624/opbanner
Project-URL: Bug Tracker, https://github.com/ghoste9624/opbanner/issues
Classifier: Programming Language :: Python :: 3
Classifier: License :: OSI Approved :: MIT License
Classifier: Operating System :: OS Independent
Classifier: Environment :: Console
Requires-Python: >=3.6
Requires-Dist: colorama
Requires-Dist: pyfiglet
Requires-Dist: prompt_toolkit
